pytc/__init__.py
pytc/fit_param.py
pytc/global_fit.py
pytc/experiments/__init__.py
pytc/experiments/base.py
pytc/global_connectors/__init__.py
pytc/global_connectors/base.py
pytc/global_connectors/num_protons.py
pytc/global_connectors/vant_hoff.py
pytc/global_connectors/vant_hoff_extended.py
pytc/indiv_models/__init__.py
pytc/indiv_models/base.py
pytc/indiv_models/binding_polynomial.py
pytc/indiv_models/blank.py
pytc/indiv_models/single_site.py
pytc/indiv_models/single_site_competitor.py
pytc/util/__init__.py
pytc/util/util.py
pytc_fitter-1.0.0.dist-info/DESCRIPTION.rst
pytc_fitter-1.0.0.dist-info/METADATA
pytc_fitter-1.0.0.dist-info/RECORD
pytc_fitter-1.0.0.dist-info/WHEEL
pytc_fitter-1.0.0.dist-info/metadata.json
pytc_fitter-1.0.0.dist-info/top_level.txt
