Metadata-Version: 2.0
Name: pytc-fitter
Version: 1.0.0
Summary: Python software package for analyzing Isothermal Titration Calorimetry data
Home-page: https://github.com/harmslab/pytc
Author: Michael J. Harms
Author-email: harmsm@gmail.com
License: UNKNOWN
Download-URL: https://github.com/harmslab/pytc/tarball/0.1.3
Platform: UNKNOWN
Classifier: Programming Language :: Python
Requires-Dist: matplotlib
Requires-Dist: numpy
Requires-Dist: pandas
Requires-Dist: scipy
